{
    "customerorder":[
      {
        "id":1,
        "orderedTimestamp":"2021-06-10T16:02:34.922+00:00",
        "remarks":null,
        "customerOrderFulfillment":
        {
          "id":1,
          "deliveredTimestamp":"2021-06-08T11:11:43.612+00:00",
          "status":"DISPATCHED",
          "expectedDateOfDelivery":null,
          "deliveryAddress":
          {
            "id":1,
            "addressLine1":"PSG Tech Boys Hostel",
            "addressLine2":"Peelamedu",
            "addressLine3":null,
            "city":"Coimbatore",
            "state":"Tamil Nadu",
            "landmark":"PSGIM",
            "phone":"9080093100",
            "pin":641004
            }
            },
            "customerOrderPayment":
            {
              "id":1,
              "amount":123.102,
              "modeOfPayment":"DEBIT_CARD",
              "paidTimestamp":"2021-06-09T16:02:34.985+00:00",
              "billingAddress":
              {
                "id":1,
                "addressLine1":"PSG Tech Boys Hostel",
                "addressLine2":"Peelamedu",
                "addressLine3":null,
                "city":"Coimbatore",
                "state":"Tamil Nadu",
                "landmark":"PSGIM",
                "phone":"9080093100",
                "pin":641004
                }
                },
                "orderedProducts":
                [
                  {
                    "id":1,
                    "units":5,
                    "status":"ORDERED",
                    "remarks":null,
                    "productId":2,
                    "productName":"Ponni",
                    "quantity":500,
                    "measurementUnit":"GRAM",
                    "batchCode":"PON0002"
                    }
                  ]
            },
            {
              "id":2,
              "orderedTimestamp":"2021-06-09T16:03:00.086+00:00",
              "remarks":null,
              "customerOrderFulfillment":
              {
                "id":2,
                "deliveredTimestamp":null,
                "status":"ORDERED",
                "expectedDateOfDelivery":null,
                "deliveryAddress":
                {
                  "id":1,
                  "addressLine1":"PSG Tech Boys Hostel",
                  "addressLine2":"Peelamedu",
                  "addressLine3":null,
                  "city":"Coimbatore",
                  "state":"Tamil Nadu",
                  "landmark":"PSGIM",
                  "phone":"9080093100",
                  "pin":641004
                  }
                  },
                  "customerOrderPayment":
                  {
                    "id":2,
                    "amount":123.102,
                    "modeOfPayment":"DEBIT_CARD",
                    "paidTimestamp":"2021-06-09T16:03:00.135+00:00",
                    "billingAddress":
                    {
                      "id":1,
                      "addressLine1":"PSG Tech Girls Hostel",
                      "addressLine2":"Peelamedu",
                      "addressLine3":null,
                      "city":"Coimbatore",
                      "state":"Tamil Nadu",
                      "landmark":"PSGIM",
                      "phone":"9080074351",
                      "pin":641004
                      }
                      },
                      "orderedProducts":
                      [
                        {
                          "id":2,
                          "units":5,
                          "status":"ORDERED",
                          "remarks":null,
                          "productId":2,
                          "productName":"Ponni",
                          "quantity":500,
                          "measurementUnit":"GRAM",
                          "batchCode":"PON0002"
                          }
                          ]
                        }   
    ]
}